telegram2rss/__about__.py
telegram2rss/__init__.py
telegram2rss/channel.py
telegram2rss/conversions.py
telegram2rss/telegram_types.py
telegram2rss-0.1.1.dist-info/LICENSE
telegram2rss-0.1.1.dist-info/METADATA
telegram2rss-0.1.1.dist-info/WHEEL
telegram2rss-0.1.1.dist-info/top_level.txt
telegram2rss-0.1.1.dist-info/RECORD
