Metadata-Version: 2.1
Name: telegram2rss
Version: 0.1.1
Summary: A python library to fetch data from public Telegram channels to use them as a python object or RSS feed.
Home-page: https://github.com/zer0-x/python-telegram2rss
Author: zer0-x
Maintainer: zer0-x
License: GPL-3.0
Project-URL: Issues, https://github.com/ZER0-X/python-telegram2rss/issues
Project-URL: Changelog, https://github.com/ZER0-X/python-telegram2rss/blob/main/CHANGELOG.md
Keywords: Python,Telegram,RSS
License-File: LICENSE
Requires-Dist: requests
Requires-Dist: beautifulsoup4
Requires-Dist: lxml
Requires-Dist: feedgen
